{"schema":{"fields":[{"name":"index","type":"integer"},{"name":"date","type":"datetime"},{"name":"holiday","type":"integer"},{"name":"min_temp","type":"string"},{"name":"max_temp","type":"string"},{"name":"rain","type":"number"},{"name":"cloud","type":"integer"},{"name":"nightOpen","type":"integer"},{"name":"culture","type":"integer"},{"name":"img","type":"string"},{"name":"wind","type":"number"},{"name":"day","type":"string"}],"primaryKey":["index"],"pandas_version":"0.20.0"},"data":[{"index":0,"date":"2021-04-22T10:17:25.249Z","holiday":0,"min_temp":"16","max_temp":"27","rain":0.0,"cloud":6,"nightOpen":0,"culture":0,"img":"\/03.png","wind":2.0,"day":"04\uc6d4 22\uc77c (\ubaa9)"},{"index":1,"date":"2021-04-23T10:17:25.249Z","holiday":0,"min_temp":"16","max_temp":"22","rain":0.1,"cloud":8,"nightOpen":0,"culture":0,"img":"\/07.png","wind":3.0,"day":"04\uc6d4 23\uc77c (\uae08)"},{"index":2,"date":"2021-04-24T10:17:25.249Z","holiday":0,"min_temp":"13","max_temp":"23","rain":0.0,"cloud":4,"nightOpen":0,"culture":0,"img":"\/21.png","wind":2.0,"day":"04\uc6d4 24\uc77c (\ud1a0)"},{"index":3,"date":"2021-04-25T10:17:25.249Z","holiday":0,"min_temp":"13","max_temp":"23","rain":0.0,"cloud":1,"nightOpen":0,"culture":0,"img":"\/01.png","wind":2.0,"day":"04\uc6d4 25\uc77c (\uc77c)"},{"index":4,"date":"2021-04-26T10:17:25.249Z","holiday":0,"min_temp":"11","max_temp":"22","rain":0.0,"cloud":2,"nightOpen":0,"culture":0,"img":"\/02.png","wind":2.0,"day":"04\uc6d4 26\uc77c (\uc6d4)"},{"index":5,"date":"2021-04-27T10:17:25.249Z","holiday":0,"min_temp":"11","max_temp":"19","rain":0.0,"cloud":2,"nightOpen":0,"culture":0,"img":"\/02.png","wind":2.0,"day":"04\uc6d4 27\uc77c (\ud654)"},{"index":6,"date":"2021-04-28T10:17:25.249Z","holiday":0,"min_temp":"11","max_temp":"20","rain":0.4,"cloud":8,"nightOpen":0,"culture":1,"img":"\/07.png","wind":2.0,"day":"04\uc6d4 28\uc77c (\uc218)"},{"index":7,"date":"2021-04-29T10:17:25.249Z","holiday":0,"min_temp":"11","max_temp":"21","rain":0.0,"cloud":2,"nightOpen":0,"culture":0,"img":"\/02.png","wind":3.0,"day":"04\uc6d4 29\uc77c (\ubaa9)"},{"index":8,"date":"2021-04-30T10:17:25.249Z","holiday":0,"min_temp":"10","max_temp":"19","rain":0.0,"cloud":1,"nightOpen":0,"culture":0,"img":"\/01.png","wind":4.0,"day":"04\uc6d4 30\uc77c (\uae08)"},{"index":9,"date":"2021-05-01T10:17:25.249Z","holiday":0,"min_temp":"10","max_temp":"20","rain":0.0,"cloud":1,"nightOpen":0,"culture":0,"img":"\/01.png","wind":3.0,"day":"05\uc6d4 01\uc77c (\ud1a0)"}]}